snappy/CyOpenGL.cpython-310-darwin.so
snappy/SnapPy.cpython-310-darwin.so
snappy/SnapPy.ico
snappy/SnapPy.png
snappy/SnapPyHP.cpython-310-darwin.so
snappy/__init__.py
snappy/app.py
snappy/app_menus.py
snappy/browser.py
snappy/cache.py
snappy/canonical.py
snappy/database.py
snappy/db_utilities.py
snappy/decorated_isosig.py
snappy/exceptions.py
snappy/export_stl.py
snappy/filedialog.py
snappy/gui.py
snappy/horoviewer.py
snappy/info_icon.gif
snappy/infowindow.py
snappy/isometry_signature.py
snappy/math_basics.py
snappy/matrix.py
snappy/number.py
snappy/numeric_output_checker.py
snappy/pari.py
snappy/phone_home.py
snappy/polyviewer.py
snappy/sage_helper.py
snappy/settings.py
snappy/shell.py
snappy/test.py
snappy/test_cases.py
snappy/testing.py
snappy/tkterminal.py
snappy/version.py
snappy/cusps/__init__.py
snappy/cusps/cusp_area_matrix.py
snappy/cusps/cusp_areas_from_matrix.py
snappy/cusps/maximal_cusp_area_matrix.py
snappy/cusps/short_slopes_for_cusp.py
snappy/cusps/test.py
snappy/cusps/trig_cusp_area_matrix.py
snappy/dev/__init__.py
snappy/dev/extended_ptolemy/__init__.py
snappy/dev/extended_ptolemy/closed.py
snappy/dev/extended_ptolemy/complexVolumesClosed.py
snappy/dev/extended_ptolemy/direct.py
snappy/dev/extended_ptolemy/extended.py
snappy/dev/extended_ptolemy/giac_helper.py
snappy/dev/extended_ptolemy/giac_rur.py
snappy/dev/extended_ptolemy/gluing.py
snappy/dev/extended_ptolemy/phc_wrapper.py
snappy/dev/extended_ptolemy/printMatrices.py
snappy/dev/vericlosed/__init__.py
snappy/dev/vericlosed/computeApproxHyperbolicStructureNew.py
snappy/dev/vericlosed/computeApproxHyperbolicStructureOrb.py
snappy/dev/vericlosed/computeVerifiedHyperbolicStructure.py
snappy/dev/vericlosed/gimbalLoopFinder.py
snappy/dev/vericlosed/hyperbolicStructure.py
snappy/dev/vericlosed/krawczykCertifiedEdgeLengthsEngine.py
snappy/dev/vericlosed/oneVertexTruncatedComplex.py
snappy/dev/vericlosed/parseVertexGramMatrixFile.py
snappy/dev/vericlosed/polishApproxHyperbolicStructure.py
snappy-3.3.dist-info/METADATA
snappy-3.3.dist-info/WHEEL
snappy-3.3.dist-info/entry_points.txt
snappy-3.3.dist-info/top_level.txt
snappy-3.3.dist-info/RECORD
