Metadata-Version: 2.1
Name: snappy
Version: 3.3
Summary: Studying the topology and geometry of 3-manifolds, with a focus on hyperbolic structures.
Home-page: http://snappy.computop.org
Author: Marc Culler and Nathan M. Dunfield
Author-email: culler@uic.edu, nathan@dunfield.info
License: GPLv2+
Keywords: 3-manifolds,topology,hyperbolic geometry
Classifier: Development Status :: 5 - Production/Stable
Classifier: Intended Audience :: Science/Research
Classifier: License :: OSI Approved :: GNU General Public License v2 or later (GPLv2+)
Classifier: Operating System :: OS Independent
Classifier: Programming Language :: C
Classifier: Programming Language :: C++
Classifier: Programming Language :: Python
Classifier: Programming Language :: Cython
Classifier: Topic :: Scientific/Engineering :: Mathematics
Requires-Python: >=3.8
Requires-Dist: FXrays>=1.3
Requires-Dist: plink>=2.4.7
Requires-Dist: spherogram>=2.4
Requires-Dist: snappy-manifolds>=1.4
Requires-Dist: low-index>=1.2.1
Requires-Dist: tkinter-gl>=1.0
Requires-Dist: decorator
Requires-Dist: packaging
Requires-Dist: pypng
Requires-Dist: PyX
Requires-Dist: pickleshare
Requires-Dist: cypari>=2.3
Requires-Dist: ipython>=5.0
